MANIFEST.in
README.md
setup.py
bin/urxvt-tabbed
urxvt_tabbed/__init__.py
urxvt_tabbed/config.py
urxvt_tabbed/gdk_events.py
urxvt_tabbed/tab_label.py
urxvt_tabbed/urxvt_tabbed.py
urxvt_tabbed.egg-info/PKG-INFO
urxvt_tabbed.egg-info/SOURCES.txt
urxvt_tabbed.egg-info/dependency_links.txt
urxvt_tabbed.egg-info/requires.txt
urxvt_tabbed.egg-info/top_level.txt