Metadata-Version: 1.1
Name: urxvt-tabbed
Version: 0.2.0
Summary: Tab wrapper for urxt
Home-page: https://github.com/simonzack/urxvt-tabbed
Author: simonzack
Author-email: simonzack@gmail.com
License: GPLv3
Platform: UNKNOWN
Classifier: Development Status :: 4 - Beta
Classifier: Intended Audience :: End Users/Desktop
Classifier: License :: OSI Approved :: GNU General Public License v3 (GPLv3)
Classifier: Programming Language :: Python :: 3
Classifier: Topic :: Terminals :: Terminal Emulators/X Terminals
